pypulse/__init__.py
pypulse/manage.py
pypulse/Aplication/__init__.py
pypulse/Aplication/aplication.py
pypulse/Aplication/get_aplication.py
pypulse/Aplication/set_aplication.py
pypulse/Aplication/vars.py
pypulse/Controller/__init__.py
pypulse/Controller/api_rest_full.py
pypulse/Controller/auth.py
pypulse/Controller/backend.py
pypulse/Controller/vars.py
pypulse/Controller/ApiRestFullAuthTypes/__init__.py
pypulse/Controller/ApiRestFullAuthTypes/api_rest_methods.py
pypulse/Controller/ApiRestFullAuthTypes/basic.py
pypulse/Model/__init__.py
pypulse/Model/data_types.py
pypulse/Model/model.py
pypulse/Model/utils.py
pypulse/Model/view.py
pypulse/Socket/__init__.py
pypulse/Socket/handler.py
pypulse/Socket/server.py
pypulse/Template/__init__.py
pypulse/Template/redirect.py
pypulse/Template/reload.py
pypulse/Template/render.py
pypulse/Template/template.py
pypulse/Utils/__init__.py
pypulse/Utils/get_apps.py
pypulse/Utils/routing.py
pypulse/View/__init__.py
pypulse/View/modules.py
pypulse/View/types.py
pypulse/View/views.py
pypulse/View/decorators/__init__.py
pypulse/View/decorators/route.py
pypulse/Window/__init__.py
pypulse/Window/app.py
pypulse/Window/cef.py
pypulse/Window/frames.py
pypulse/Window/load_browser.py
pypulse/Window/logger.py
python_pulse-0.4.1.dist-info/LICENSE
python_pulse-0.4.1.dist-info/METADATA
python_pulse-0.4.1.dist-info/WHEEL
python_pulse-0.4.1.dist-info/entry_points.txt
python_pulse-0.4.1.dist-info/top_level.txt
python_pulse-0.4.1.dist-info/RECORD
