Metadata-Version: 2.1
Name: python-pulse
Version: 0.4.1
Summary: Open-source project that simplifies the creation of desktop applications based on Chromium
Author: Vasile Ovidiu Ichim
License: MIT
Classifier: Development Status :: 5 - Production/Stable
Classifier: Intended Audience :: Developers
Classifier: Topic :: Software Development :: Build Tools
Classifier: License :: OSI Approved :: MIT License
Classifier: Programming Language :: Python :: 3.8
Classifier: Programming Language :: Python :: 3.9
License-File: LICENSE
Requires-Dist: cefpython3==66.1
Requires-Dist: Jinja2==3.1.2
Requires-Dist: wxPython==4.2.1
Requires-Dist: requests
